secrypto/__init__.py
secrypto/source/decrypt.py
secrypto/source/encrypt.py
secrypto/source/key.py
secrypto-1.1.0.dist-info/licenses/LICENSE.md
secrypto-1.1.0.dist-info/METADATA
secrypto-1.1.0.dist-info/WHEEL
secrypto-1.1.0.dist-info/top_level.txt
secrypto-1.1.0.dist-info/RECORD
