Metadata-Version: 2.4
Name: secrypto
Version: 1.1.0
Summary: A powerful encryption and decryption library
Author: Aahan Salecha
License: CC0 1.0 Universal
Project-URL: Source Repository, https://github.com/aahan0511/Secrypto/
License-File: LICENSE.md
Dynamic: author
Dynamic: description
Dynamic: description-content-type
Dynamic: license
Dynamic: license-file
Dynamic: project-url
Dynamic: summary
